reolink_ip/__init__.py
reolink_ip/api.py
reolink_ip/exceptions.py
reolink_ip/software_version.py
reolink_ip/templates.py
reolink_ip/typings.py
reolink_ip-0.0.49.dist-info/LICENSE
reolink_ip-0.0.49.dist-info/METADATA
reolink_ip-0.0.49.dist-info/WHEEL
reolink_ip-0.0.49.dist-info/top_level.txt
reolink_ip-0.0.49.dist-info/RECORD
