Metadata-Version: 2.1
Name: reolink-ip
Version: 0.0.49
Summary: Reolink IP NVR/camera API
Author-email: JimStar <bubukis@gmail.com>
License: MIT License
Project-URL: homepage, https://github.com/JimStar/reolink_ip
Project-URL: repository, https://github.com/JimStar/reolink_ip/releases/latest
Keywords: Reolink,API,camera,NVR,CCTV,Home-Assistant,Home Assistant,Smart Home
Classifier: Development Status :: 4 - Beta
Classifier: Intended Audience :: Developers
Classifier: Topic :: Software Development :: Build Tools
Classifier: Programming Language :: Python
Classifier: Programming Language :: Python :: 3.9
Classifier: License :: OSI Approved :: MIT License
Classifier: Operating System :: OS Independent
Requires-Python: >=3.9
License-File: LICENSE
Requires-Dist: ffmpeg
Requires-Dist: requests
Requires-Dist: aiohttp
